odoo/addons/shopfloor/README.rst
odoo/addons/shopfloor/__init__.py
odoo/addons/shopfloor/__manifest__.py
odoo/addons/shopfloor/exceptions.py
odoo/addons/shopfloor/utils.py
odoo/addons/shopfloor/actions/__init__.py
odoo/addons/shopfloor/actions/barcode_parser.py
odoo/addons/shopfloor/actions/change_package_lot.py
odoo/addons/shopfloor/actions/completion_info.py
odoo/addons/shopfloor/actions/data.py
odoo/addons/shopfloor/actions/data_detail.py
odoo/addons/shopfloor/actions/inventory.py
odoo/addons/shopfloor/actions/location_content_transfer_sorter.py
odoo/addons/shopfloor/actions/message.py
odoo/addons/shopfloor/actions/move_line_search.py
odoo/addons/shopfloor/actions/packing.py
odoo/addons/shopfloor/actions/savepoint.py
odoo/addons/shopfloor/actions/schema.py
odoo/addons/shopfloor/actions/schema_detail.py
odoo/addons/shopfloor/actions/search.py
odoo/addons/shopfloor/actions/stock.py
odoo/addons/shopfloor/actions/stock_unreserve.py
odoo/addons/shopfloor/components/__init__.py
odoo/addons/shopfloor/components/scan_handler_location.py
odoo/addons/shopfloor/components/scan_handler_lot.py
odoo/addons/shopfloor/components/scan_handler_package.py
odoo/addons/shopfloor/components/scan_handler_product.py
odoo/addons/shopfloor/components/scan_handler_transfer.py
odoo/addons/shopfloor/data/shopfloor_scenario_data.xml
odoo/addons/shopfloor/demo/shopfloor_app_demo.xml
odoo/addons/shopfloor/demo/shopfloor_menu_demo.xml
odoo/addons/shopfloor/demo/shopfloor_profile_demo.xml
odoo/addons/shopfloor/demo/stock_picking_type_demo.xml
odoo/addons/shopfloor/docs/checkout_diag_seq.plantuml
odoo/addons/shopfloor/docs/checkout_diag_seq.png
odoo/addons/shopfloor/docs/cluster_picking_diag_seq.plantuml
odoo/addons/shopfloor/docs/cluster_picking_diag_seq.png
odoo/addons/shopfloor/docs/delivery_diag_seq.plantuml
odoo/addons/shopfloor/docs/delivery_diag_seq.png
odoo/addons/shopfloor/docs/location_content_transfer_diag_seq.plantuml
odoo/addons/shopfloor/docs/location_content_transfer_diag_seq.png
odoo_addon_shopfloor-18.0.0.9.1.dist-info/METADATA
odoo_addon_shopfloor-18.0.0.9.1.dist-info/WHEEL
odoo_addon_shopfloor-18.0.0.9.1.dist-info/top_level.txt
odoo_addon_shopfloor-18.0.0.9.1.dist-info/RECORD
