Metadata-Version: 2.1
Name: odoo-addon-shopfloor
Version: 18.0.0.9.1
Requires-Python: >=3.10
Requires-Dist: odoo-addon-base_rest==18.0.*
Requires-Dist: odoo-addon-jsonifier==18.0.*
Requires-Dist: odoo-addon-product_manufacturer==18.0.*
Requires-Dist: odoo-addon-product_packaging_level==18.0.*
Requires-Dist: odoo-addon-shopfloor_base==18.0.*
Requires-Dist: odoo-addon-stock_location_is_sublocation==18.0.*
Requires-Dist: odoo-addon-stock_move_line_change_lot==18.0.*
Requires-Dist: odoo-addon-stock_move_line_qty_picked==18.0.*
Requires-Dist: odoo-addon-stock_picking_completion_info==18.0.*
Requires-Dist: odoo-addon-stock_picking_delivery_link==18.0.*
Requires-Dist: odoo-addon-stock_picking_progress==18.0.*
Requires-Dist: odoo-addon-stock_quant_package_dimension==18.0.*
Requires-Dist: odoo-addon-stock_quant_package_product_packaging==18.0.*
Requires-Dist: odoo-addon-stock_storage_type==18.0.*
Requires-Dist: odoo==18.0.*
Summary: manage warehouse operations with barcode scanners
Home-page: https://github.com/OCA/stock-logistics-shopfloor
License: AGPL-3
Author: Camptocamp, BCIM, Akretion, Odoo Community Association (OCA)
Author-email: support@odoo-community.org
Classifier: Programming Language :: Python
Classifier: Framework :: Odoo
Classifier: Framework :: Odoo :: 18.0
Classifier: License :: OSI Approved :: GNU Affero General Public License v3
Classifier: Development Status :: 4 - Beta
